sagebase/__init__.py
sagebase/ansible.cfg
sagebase/bootstrap.sh
sagebase/terminate.sh
sagebase/util.sh
sagebase/.ssh/pkey.pem
sagebase/inventory/stage/ec2.ini
sagebase/inventory/stage/ec2.py
sagebase/inventory/stage/group_vars/all/ebs_optimized_types.yml
sagebase/inventory/stage/group_vars/all/valid_instance_types.yml
sagebase/library/block_device_mapping.py
sagebase/library/ec2.py
sagebase/playbooks/provision/bootstrap.retry
sagebase/playbooks/provision/bootstrap.yml
sagebase/playbooks/provision/terminate.yml
sagebase/playbooks/sage/install.yml
sagebase/playbooks/webserver/install.retry
sagebase/plugins/lookups/hosts_by_service.py
sagebase/plugins/lookups/instance_name_mapping.py
sagebase/plugins/lookups/__pycache__/hosts_by_service.cpython-37.pyc
sagebase/plugins/lookups/__pycache__/instance_name_mapping.cpython-37.pyc
sagebase/roles/jupyter.installer/tasks/main.yml
sagebase/roles/nvidia.installer/tasks/main.yml
sagebase/roles/provision.post-tasks/tasks/main.yml
sagebase/roles/sage.initializer/tasks/main.yml
sagebase/roles/sage.installer/defaults/main.yml
sagebase/roles/sage.installer/files/requirements.txt
sagebase/roles/sage.installer/files/sample_notebook.ipynb
sagebase/roles/sage.installer/meta/main.yml
sagebase/roles/sage.installer/tasks/main.yml
sagebase/templates/config.yml
sagebase/templates/user_data.sh
sagecreator/__init__.py
sagecreator/configurator.py
sagecreator/provisioner.py
scripts/__init__.py
scripts/cli.py
tests/__init__.py
tests/test_configurator.py
tests/test_provisioner.py
sagecreator-0.1.1.6.dist-info/METADATA
sagecreator-0.1.1.6.dist-info/WHEEL
sagecreator-0.1.1.6.dist-info/entry_points.txt
sagecreator-0.1.1.6.dist-info/top_level.txt
sagecreator-0.1.1.6.dist-info/RECORD
