Metadata-Version: 2.1
Name: sagecreator
Version: 0.1.1.6
Summary: Package to orchestrate architecture in AWS
Home-page: https://github.com/romanjoffee/sagecreator
Author: romanjoffee
Author-email: roman.jugai@gmail.com
License: UNKNOWN
Platform: UNKNOWN
Classifier: Programming Language :: Python :: 3
Classifier: License :: OSI Approved :: Apache Software License
Classifier: Operating System :: OS Independent
Requires-Dist: ansible (==2.7.8)
Requires-Dist: boto (==2.49.0)
Requires-Dist: boto3 (==1.9.82)
Requires-Dist: botocore (==1.12.82)
Requires-Dist: click (==7.0)
Requires-Dist: pyyaml (==5.1)
